{
  "headers": {
    "x-amz-cf-pop": "SEA73-P3",
    "x-amz-version-id": "WDwMnhv_ha3Nbz2ljc.iDmfKmUo4f8vN",
    "x-cache": "Hit from cloudfront",
    "etag": "\"edcb41588c63f5c06e3e4d8ec40d19cd\"",
    "content-length": "541",
    "cross-origin-resource-policy": "same-origin",
    "x-amz-cf-id": "tKW4SlLdtWFupuBbiLN_BH09TNVKvi8xaFOcL7mHAJ2SKhvRwLULUg==",
    "x-amz-replication-status": "COMPLETED",
    "x-amz-server-side-encryption": "AES256",
    "x-content-type-options": "nosniff",
    "x-frame-options": "DENY",
    "content-security-policy": "default-src 'none'; style-src 'unsafe-inline'; sandbox",
    "date": "Mon, 13 Nov 2023 05:38:20 GMT",
    "referrer-policy": "strict-origin-when-cross-origin",
    "vary": "Accept-Encoding, Origin",
    "strict-transport-security": "max-age=63072000; includeSubDomains; preload",
    "server-timing": "fetchSource;dur=24",
    "via": "http/2 edgeproxy-h",
    "cross-origin-embedder-policy": "same-origin",
    "last-modified": "Mon, 13 Nov 2023 05:30:32 GMT",
    "cross-origin-opener-policy": "same-origin",
    "content-type": "application/typescript; charset=utf-8",
    "server": "deno/gcp-us-west1",
    "accept-ranges": "bytes",
    "cache-control": "public, max-age=31536000, immutable",
    "access-control-allow-origin": "*",
    "age": "65186"
  },
  "url": "https://deno.land/x/hono@v3.10.0/http-exception.ts",
  "now": {
    "secs_since_epoch": 1699919086,
    "nanos_since_epoch": 359614722
  }
}